LICENSE
README.md
setup.cfg
setup.py
he5py/CMakeLists.txt
he5py/HDF5.py
he5py/HDFEOS5.py
he5py/__init__.py
he5py/he5py.py
he5py/version.txt
he5py.egg-info/PKG-INFO
he5py.egg-info/SOURCES.txt
he5py.egg-info/dependency_links.txt
he5py.egg-info/not-zip-safe
he5py.egg-info/requires.txt
he5py.egg-info/top_level.txt
he5py/include/he5py.hpp
he5py/src/CMakeLists.txt
he5py/src/he5py.cpp
he5py/src/cmake/FindHDFEOS5.cmake
he5py/src/cmake/FindNumPy.cmake
he5py/src/cmake/Findpybind11.cmake
he5py/src/pybind11/CMakeLists.txt
he5py/src/pybind11/LICENSE
he5py/src/pybind11/MANIFEST.in
he5py/src/pybind11/README.rst
he5py/src/pybind11/SECURITY.md
he5py/src/pybind11/noxfile.py
he5py/src/pybind11/pyproject.toml
he5py/src/pybind11/setup.cfg
he5py/src/pybind11/setup.py
he5py/src/pybind11/docs/Doxyfile
he5py/src/pybind11/docs/Makefile
he5py/src/pybind11/docs/basics.rst
he5py/src/pybind11/docs/benchmark.py
he5py/src/pybind11/docs/benchmark.rst
he5py/src/pybind11/docs/changelog.rst
he5py/src/pybind11/docs/classes.rst
he5py/src/pybind11/docs/compiling.rst
he5py/src/pybind11/docs/conf.py
he5py/src/pybind11/docs/faq.rst
he5py/src/pybind11/docs/index.rst
he5py/src/pybind11/docs/installing.rst
he5py/src/pybind11/docs/limitations.rst
he5py/src/pybind11/docs/pybind11-logo.png
he5py/src/pybind11/docs/pybind11_vs_boost_python1.png
he5py/src/pybind11/docs/pybind11_vs_boost_python1.svg
he5py/src/pybind11/docs/pybind11_vs_boost_python2.png
he5py/src/pybind11/docs/pybind11_vs_boost_python2.svg
he5py/src/pybind11/docs/reference.rst
he5py/src/pybind11/docs/release.rst
he5py/src/pybind11/docs/requirements.txt
he5py/src/pybind11/docs/upgrade.rst
he5py/src/pybind11/docs/_static/css/custom.css
he5py/src/pybind11/docs/advanced/classes.rst
he5py/src/pybind11/docs/advanced/embedding.rst
he5py/src/pybind11/docs/advanced/exceptions.rst
he5py/src/pybind11/docs/advanced/functions.rst
he5py/src/pybind11/docs/advanced/misc.rst
he5py/src/pybind11/docs/advanced/smart_ptrs.rst
he5py/src/pybind11/docs/advanced/cast/chrono.rst
he5py/src/pybind11/docs/advanced/cast/custom.rst
he5py/src/pybind11/docs/advanced/cast/eigen.rst
he5py/src/pybind11/docs/advanced/cast/functional.rst
