Metadata-Version: 2.1
Name: he5py
Version: 1.0.6
Summary: Utilities for working with the HDF-EOS-5 remote sensing data format
Author: Gregory Halverson
Author-email: Gregory.H.Halverson@jpl.nasa.gov
License-File: LICENSE
Requires-Dist: affine
Requires-Dist: colored-logging
Requires-Dist: h5py
Requires-Dist: numpy
Requires-Dist: pybind11_cmake
Requires-Dist: rasters
